zenify/__init__.py
zenify/charts.py
zenify/clean_data.py
zenify/cli.py
zenify/config.py
zenify/easing.py
zenify/history.py
zenify/language.py
zenify/main.py
zenify/shapes.py
zenify/ui.py
zenify-1.0.3.dist-info/licenses/LICENSE
zenify-1.0.3.dist-info/METADATA
zenify-1.0.3.dist-info/WHEEL
zenify-1.0.3.dist-info/entry_points.txt
zenify-1.0.3.dist-info/top_level.txt
zenify-1.0.3.dist-info/RECORD
