Metadata-Version: 2.4
Name: zenify
Version: 1.0.3
Summary: 🧘 A beautiful terminal meditation app with ASCII art, multi-language support, and breathing exercises
Home-page: https://github.com/kawarox/zenify
Author: Zenify Team
Author-email: Zenify Team <zenify.meditation@gmail.com>
License: MIT
Project-URL: Homepage, https://github.com/kawarox/zenify
Project-URL: Bug Reports, https://github.com/kawarox/zenify/issues
Project-URL: Source, https://github.com/kawarox/zenify
Project-URL: Documentation, https://github.com/kawarox/zenify/blob/main/README.md
Keywords: meditation,mindfulness,terminal,ascii,wellness,health,breathing,zen,relaxation
Classifier: Development Status :: 5 - Production/Stable
Classifier: Environment :: Console
Classifier: Intended Audience :: End Users/Desktop
Classifier: Topic :: Other/Nonlisted Topic
Classifier: Topic :: Utilities
Classifier: License :: OSI Approved :: MIT License
Classifier: Natural Language :: Chinese (Simplified)
Classifier: Natural Language :: English
Classifier: Natural Language :: Japanese
Classifier: Operating System :: OS Independent
Classifier: Programming Language :: Python :: 3
Classifier: Programming Language :: Python :: 3.6
Classifier: Programming Language :: Python :: 3.7
Classifier: Programming Language :: Python :: 3.8
Classifier: Programming Language :: Python :: 3.9
Classifier: Programming Language :: Python :: 3.10
Classifier: Programming Language :: Python :: 3.11
Classifier: Programming Language :: Python :: 3.12
Requires-Python: >=3.6
License-File: LICENSE
Dynamic: author
Dynamic: home-page
Dynamic: license-file
Dynamic: requires-python
